{
  "chartExports": [
    {
      "chart": {
        "created": 0,
        "creator": null,
        "customProperties": {},
        "description": "CPU Utilization of the service hosts",
        "id": "DupO1ITAgAA",
        "lastUpdated": 0,
        "lastUpdatedBy": null,
        "name": "Host CPU",
        "options": {
          "areaChartOptions": {
            "showDataMarkers": false
          },
          "axes": [
            {
              "highWatermark": null,
              "highWatermarkLabel": null,
              "label": "%",
              "lowWatermark": null,
              "lowWatermarkLabel": null,
              "max": 100,
              "min": 0
            },
            {
              "highWatermark": null,
              "highWatermarkLabel": null,
              "label": "",
              "lowWatermark": null,
              "lowWatermarkLabel": null,
              "max": null,
              "min": null
            }
          ],
          "axisPrecision": null,
          "colorBy": "Dimension",
          "defaultPlotType": "LineChart",
          "eventPublishLabelOptions": [],
          "histogramChartOptions": {
            "colorThemeIndex": 16
          },
          "includeZero": false,
          "legendOptions": {
            "fields": null
          },
          "lineChartOptions": {
            "showDataMarkers": false
          },
          "onChartLegendOptions": {
            "dimensionInLegend": null,
            "showLegend": false
          },
          "programOptions": {
            "disableSampling": false,
            "maxDelay": 0,
            "minimumResolution": 0
          },
          "publishLabelOptions": [
            {
              "displayName": "cpu.utilization",
              "label": "A",
              "paletteIndex": null,
              "plotType": null,
              "valuePrefix": "",
              "valueSuffix": "",
              "valueUnit": null,
              "yAxis": 0
            }
          ],
          "showEventLines": false,
          "stacked": false,
          "time": {
            "range": 900000,
            "type": "relative"
          },
          "timezone": null,
          "type": "TimeSeriesChart",
          "unitPrefix": "Metric"
        },
        "packageSpecifications": "",
        "programText": "A = data('cpu.utilization', filter=filter('sf_hasService', '*')).publish(label='A')",
        "relatedDetectorIds": [],
        "tags": null
      }
    },
    {
      "chart": {
        "created": 0,
        "creator": null,
        "customProperties": {},
        "description": "Memory utilization of the service hosts",
        "id": "DsK5pd_AcFg",
        "importOf": "Dr64aTDAAAE",
        "lastUpdated": 0,
        "lastUpdatedBy": null,
        "name": "Host memory usage",
        "options": {
          "areaChartOptions": {
            "showDataMarkers": false
          },
          "axes": [
            {
              "highWatermark": null,
              "highWatermarkLabel": null,
              "label": "%",
              "lowWatermark": null,
              "lowWatermarkLabel": null,
              "max": 100,
              "min": 0
            },
            {
              "highWatermark": null,
              "highWatermarkLabel": null,
              "label": "",
              "lowWatermark": null,
              "lowWatermarkLabel": null,
              "max": null,
              "min": null
            }
          ],
          "axisPrecision": null,
          "colorBy": "Dimension",
          "defaultPlotType": "LineChart",
          "eventPublishLabelOptions": [],
          "histogramChartOptions": {
            "colorThemeIndex": 16
          },
          "includeZero": false,
          "legendOptions": {
            "fields": null
          },
          "lineChartOptions": {
            "showDataMarkers": false
          },
          "onChartLegendOptions": {
            "dimensionInLegend": null,
            "showLegend": false
          },
          "programOptions": {
            "disableSampling": false,
            "maxDelay": 0,
            "minimumResolution": 0
          },
          "publishLabelOptions": [
            {
              "displayName": "memory.utilization",
              "label": "A",
              "paletteIndex": null,
              "plotType": null,
              "valuePrefix": "",
              "valueSuffix": "",
              "valueUnit": null,
              "yAxis": 0
            }
          ],
          "showEventLines": false,
          "stacked": false,
          "time": {
            "range": 900000,
            "type": "relative"
          },
          "timezone": null,
          "type": "TimeSeriesChart",
          "unitPrefix": "Metric"
        },
        "packageSpecifications": "",
        "programText": "A = data('memory.utilization', filter=filter('sf_hasService', '*')).publish(label='A')",
        "relatedDetectorIds": [],
        "tags": null
      }
    },
    {
      "chart": {
        "created": 0,
        "creator": null,
        "customProperties": {},
        "description": "Requests/sec processed by the service",
        "id": "DsK5oLZAcAA",
        "importOf": "DqlPwItAEAA",
        "lastUpdated": 0,
        "lastUpdatedBy": null,
        "name": "Request rate",
        "options": {
          "areaChartOptions": {
            "showDataMarkers": false
          },
          "axes": [
            {
              "highWatermark": null,
              "highWatermarkLabel": null,
              "label": "",
              "lowWatermark": null,
              "lowWatermarkLabel": null,
              "max": null,
              "min": null
            },
            {
              "highWatermark": null,
              "highWatermarkLabel": null,
              "label": "",
              "lowWatermark": null,
              "lowWatermarkLabel": null,
              "max": null,
              "min": null
            }
          ],
          "axisPrecision": null,
          "colorBy": "Dimension",
          "defaultPlotType": "LineChart",
          "eventPublishLabelOptions": [],
          "histogramChartOptions": {
            "colorThemeIndex": 16
          },
          "includeZero": false,
          "legendOptions": {
            "fields": null
          },
          "lineChartOptions": {
            "showDataMarkers": false
          },
          "onChartLegendOptions": {
            "dimensionInLegend": null,
            "showLegend": false
          },
          "programOptions": {
            "disableSampling": false,
            "maxDelay": null,
            "minimumResolution": 0
          },
          "publishLabelOptions": [
            {
              "displayName": "Requests/sec",
              "label": "A",
              "paletteIndex": null,
              "plotType": null,
              "valuePrefix": null,
              "valueSuffix": "requests/sec",
              "valueUnit": null,
              "yAxis": 0
            }
          ],
          "showEventLines": false,
          "stacked": false,
          "time": {
            "range": 900000,
            "type": "relative"
          },
          "timezone": null,
          "type": "TimeSeriesChart",
          "unitPrefix": "Metric"
        },
        "packageSpecifications": "",
        "programText": "A = data('spans.count', filter=filter('kind', 'SERVER', 'CONSUMER') and filter('service', '*')).sum(by=['service']).publish(label='A')",
        "relatedDetectorIds": [],
        "tags": null
      }
    },
    {
      "chart": {
        "created": 0,
        "creator": null,
        "customProperties": {},
        "description": "Error rate on requests made to the service",
        "id": "DsK5qJnAcA8",
        "importOf": "DqlZTecAIAA",
        "lastUpdated": 0,
        "lastUpdatedBy": null,
        "name": "Error rate",
        "options": {
          "colorBy": "Scale",
          "colorScale": null,
          "colorScale2": [
            {
              "gt": 5,
              "gte": null,
              "lt": null,
              "lte": null,
              "paletteIndex": 16
            },
            {
              "gt": 1,
              "gte": null,
              "lt": null,
              "lte": 5,
              "paletteIndex": 17
            },
            {
              "gt": 0,
              "gte": null,
              "lt": null,
              "lte": 1,
              "paletteIndex": 18
            },
            {
              "gt": null,
              "gte": null,
              "lt": null,
              "lte": 0,
              "paletteIndex": 20
            }
          ],
          "maximumPrecision": null,
          "programOptions": {
            "disableSampling": false,
            "maxDelay": null,
            "minimumResolution": 0
          },
          "publishLabelOptions": [
            {
              "displayName": "Requests",
              "label": "A",
              "paletteIndex": null,
              "plotType": null,
              "valuePrefix": null,
              "valueSuffix": null,
              "valueUnit": null,
              "yAxis": 0
            },
            {
              "displayName": "Requests",
              "label": "B",
              "paletteIndex": null,
              "plotType": null,
              "valuePrefix": null,
              "valueSuffix": null,
              "valueUnit": null,
              "yAxis": 0
            },
            {
              "displayName": "100*B/A",
              "label": "C",
              "paletteIndex": null,
              "plotType": null,
              "valuePrefix": null,
              "valueSuffix": "%",
              "valueUnit": null,
              "yAxis": 0
            }
          ],
          "refreshInterval": null,
          "secondaryVisualization": "None",
          "showSparkLine": false,
          "time": {
            "range": 900000,
            "type": "relative"
          },
          "timestampHidden": false,
          "timezone": null,
          "type": "SingleValue",
          "unitPrefix": "Metric"
        },
        "packageSpecifications": "",
        "programText": "A = data('spans.count', filter=filter('kind', 'SERVER', 'CONSUMER') and filter('error', 'false') and filter('service', '*')).sum(by=['service']).publish(label='A', enable=False)\nB = data('spans.count', filter=filter('kind', 'SERVER', 'CONSUMER') and filter('error', 'true') and filter('service', '*')).sum(by=['service']).publish(label='B', enable=False)\nC = (100*B/A).publish(label='C')",
        "relatedDetectorIds": [],
        "tags": null
      }
    },
    {
      "chart": {
        "created": 0,
        "creator": null,
        "customProperties": {},
        "description": "Distribution of request latency with median (50th), 90th and 99th percentiles",
        "id": "DsK5pkeAcEo",
        "importOf": "DqlkkqXAAAA",
        "lastUpdated": 0,
        "lastUpdatedBy": null,
        "name": "Request latency distribution",
        "options": {
          "areaChartOptions": {
            "showDataMarkers": false
          },
          "axes": [
            {
              "highWatermark": null,
              "highWatermarkLabel": null,
              "label": "",
              "lowWatermark": null,
              "lowWatermarkLabel": null,
              "max": null,
              "min": null
            },
            {
              "highWatermark": null,
              "highWatermarkLabel": null,
              "label": "",
              "lowWatermark": null,
              "lowWatermarkLabel": null,
              "max": null,
              "min": null
            }
          ],
          "axisPrecision": null,
          "colorBy": "Metric",
          "defaultPlotType": "LineChart",
          "eventPublishLabelOptions": [],
          "histogramChartOptions": {
            "colorThemeIndex": 16
          },
          "includeZero": false,
          "legendOptions": {
            "fields": null
          },
          "lineChartOptions": {
            "showDataMarkers": false
          },
          "onChartLegendOptions": {
            "dimensionInLegend": null,
            "showLegend": false
          },
          "programOptions": {
            "disableSampling": false,
            "maxDelay": null,
            "minimumResolution": 0
          },
          "publishLabelOptions": [
            {
              "displayName": "p50 latency",
              "label": "A",
              "paletteIndex": null,
              "plotType": null,
              "valuePrefix": null,
              "valueSuffix": null,
              "valueUnit": "Nanosecond",
              "yAxis": 0
            },
            {
              "displayName": "p90 latency",
              "label": "B",
              "paletteIndex": null,
              "plotType": null,
              "valuePrefix": null,
              "valueSuffix": null,
              "valueUnit": "Nanosecond",
              "yAxis": 0
            },
            {
              "displayName": "p99 latency",
              "label": "C",
              "paletteIndex": null,
              "plotType": null,
              "valuePrefix": null,
              "valueSuffix": null,
              "valueUnit": "Nanosecond",
              "yAxis": 0
            }
          ],
          "showEventLines": false,
          "stacked": false,
          "time": {
            "range": 900000,
            "type": "relative"
          },
          "timezone": null,
          "type": "TimeSeriesChart",
          "unitPrefix": "Metric"
        },
        "packageSpecifications": "",
        "programText": "A = data('spans.duration.ns.median', filter=filter('kind', 'CONSUMER', 'SERVER') and filter('service', '*') and filter('operation', '*')).mean(by=['service', 'operation']).publish(label='A')\nB = data('spans.duration.ns.p90', filter=filter('kind', 'CONSUMER', 'SERVER') and filter('service', '*') and filter('operation', '*')).mean(by=['service', 'operation']).publish(label='B')\nC = data('spans.duration.ns.p99', filter=filter('kind', 'CONSUMER', 'SERVER') and filter('service', '*') and filter('operation', '*')).mean(by=['service', 'operation']).publish(label='C')",
        "relatedDetectorIds": [],
        "tags": null
      }
    },
    {
      "chart": {
        "created": 0,
        "creator": null,
        "customProperties": {},
        "description": "99th percentile response time",
        "id": "DsK5of0AcAA",
        "importOf": "Dqlm3FrAIAA",
        "lastUpdated": 0,
        "lastUpdatedBy": null,
        "name": "Request latency (p99)",
        "options": {
          "colorBy": "Metric",
          "colorScale": null,
          "colorScale2": null,
          "maximumPrecision": 6,
          "programOptions": {
            "disableSampling": false,
            "maxDelay": null,
            "minimumResolution": 0
          },
          "publishLabelOptions": [
            {
              "displayName": "p99 latency",
              "label": "A",
              "paletteIndex": null,
              "plotType": null,
              "valuePrefix": null,
              "valueSuffix": null,
              "valueUnit": "Nanosecond",
              "yAxis": 0
            }
          ],
          "refreshInterval": null,
          "secondaryVisualization": "Sparkline",
          "showSparkLine": false,
          "time": {
            "range": 900000,
            "type": "relative"
          },
          "timestampHidden": false,
          "timezone": null,
          "type": "SingleValue",
          "unitPrefix": "Metric"
        },
        "packageSpecifications": "",
        "programText": "A = data('spans.duration.ns.p99', filter=filter('kind', 'CONSUMER', 'SERVER') and filter('service', '*') and filter('operation', '*')).mean(by=['service', 'operation']).publish(label='A')",
        "relatedDetectorIds": [],
        "tags": null
      }
    },
    {
      "chart": {
        "created": 0,
        "creator": null,
        "customProperties": {},
        "description": "Cumulative network utilization of the service hosts",
        "id": "DsK5rG5AcAE",
        "importOf": "Dr_96JaAAAA",
        "lastUpdated": 0,
        "lastUpdatedBy": null,
        "name": "Host network utilization",
        "options": {
          "areaChartOptions": {
            "showDataMarkers": false
          },
          "axes": [
            {
              "highWatermark": null,
              "highWatermarkLabel": null,
              "label": "",
              "lowWatermark": null,
              "lowWatermarkLabel": null,
              "max": null,
              "min": 0
            },
            {
              "highWatermark": null,
              "highWatermarkLabel": null,
              "label": "",
              "lowWatermark": null,
              "lowWatermarkLabel": null,
              "max": null,
              "min": null
            }
          ],
          "axisPrecision": null,
          "colorBy": "Dimension",
          "defaultPlotType": "LineChart",
          "eventPublishLabelOptions": [],
          "histogramChartOptions": {
            "colorThemeIndex": 16
          },
          "includeZero": false,
          "legendOptions": {
            "fields": null
          },
          "lineChartOptions": {
            "showDataMarkers": false
          },
          "onChartLegendOptions": {
            "dimensionInLegend": null,
            "showLegend": false
          },
          "programOptions": {
            "disableSampling": false,
            "maxDelay": 0,
            "minimumResolution": 0
          },
          "publishLabelOptions": [
            {
              "displayName": "Network utilization",
              "label": "A",
              "paletteIndex": null,
              "plotType": null,
              "valuePrefix": null,
              "valueSuffix": null,
              "valueUnit": "Byte",
              "yAxis": 0
            }
          ],
          "showEventLines": false,
          "stacked": false,
          "time": {
            "range": 900000,
            "type": "relative"
          },
          "timezone": null,
          "type": "TimeSeriesChart",
          "unitPrefix": "Metric"
        },
        "packageSpecifications": "",
        "programText": "A = data('network.total', filter=filter('sf_hasService', '*')).publish(label='A')",
        "relatedDetectorIds": [],
        "tags": null
      }
    },
    {
      "chart": {
        "created": 0,
        "creator": null,
        "customProperties": {},
        "description": "Most active service endpoints (1min requests/sec average)",
        "id": "DupNkWLAcAA",
        "lastUpdated": 0,
        "lastUpdatedBy": null,
        "name": "Top endpoints",
        "options": {
          "colorBy": "Dimension",
          "colorScale2": null,
          "legendOptions": {
            "fields": null
          },
          "maximumPrecision": null,
          "programOptions": {
            "disableSampling": false,
            "maxDelay": null,
            "minimumResolution": 0
          },
          "publishLabelOptions": [
            {
              "displayName": "Requests/sec",
              "label": "A",
              "paletteIndex": null,
              "plotType": null,
              "valuePrefix": null,
              "valueSuffix": "requests/sec",
              "valueUnit": null,
              "yAxis": 0
            }
          ],
          "refreshInterval": null,
          "secondaryVisualization": "Sparkline",
          "sortBy": "",
          "time": {
            "range": 900000,
            "type": "relative"
          },
          "timezone": null,
          "type": "List",
          "unitPrefix": "Metric"
        },
        "packageSpecifications": "",
        "programText": "A = data('spans.count', filter=filter('kind', 'SERVER', 'CONSUMER') and filter('service', '*')).sum(by=['operation', 'service']).mean(over='1m').publish(label='A')",
        "relatedDetectorIds": [],
        "tags": null
      }
    },
    {
      "chart": {
        "created": 0,
        "creator": null,
        "customProperties": {},
        "description": "Disk utilization of the service hosts",
        "id": "DsK5owAAcGI",
        "importOf": "DsAX03uAAAA",
        "lastUpdated": 0,
        "lastUpdatedBy": null,
        "name": "Host disk usage",
        "options": {
          "areaChartOptions": {
            "showDataMarkers": false
          },
          "axes": [
            {
              "highWatermark": null,
              "highWatermarkLabel": null,
              "label": "%",
              "lowWatermark": null,
              "lowWatermarkLabel": null,
              "max": 100,
              "min": 0
            },
            {
              "highWatermark": null,
              "highWatermarkLabel": null,
              "label": "",
              "lowWatermark": null,
              "lowWatermarkLabel": null,
              "max": null,
              "min": null
            }
          ],
          "axisPrecision": null,
          "colorBy": "Dimension",
          "defaultPlotType": "LineChart",
          "eventPublishLabelOptions": [],
          "histogramChartOptions": {
            "colorThemeIndex": 16
          },
          "includeZero": false,
          "legendOptions": {
            "fields": null
          },
          "lineChartOptions": {
            "showDataMarkers": false
          },
          "onChartLegendOptions": {
            "dimensionInLegend": null,
            "showLegend": false
          },
          "programOptions": {
            "disableSampling": false,
            "maxDelay": 0,
            "minimumResolution": 0
          },
          "publishLabelOptions": [
            {
              "displayName": "disk.summary_utilization",
              "label": "A",
              "paletteIndex": null,
              "plotType": null,
              "valuePrefix": "",
              "valueSuffix": "",
              "valueUnit": null,
              "yAxis": 0
            }
          ],
          "showEventLines": false,
          "stacked": false,
          "time": {
            "range": 900000,
            "type": "relative"
          },
          "timezone": null,
          "type": "TimeSeriesChart",
          "unitPrefix": "Metric"
        },
        "packageSpecifications": "",
        "programText": "A = data('disk.summary_utilization', filter=filter('sf_hasService', '*')).publish(label='A')",
        "relatedDetectorIds": [],
        "tags": null
      }
    },
    {
      "chart": {
        "created": 0,
        "creator": null,
        "customProperties": {},
        "description": "Saturation of the service hosts (max of CPU, memory and disk utilization)",
        "id": "DsK5ou1AcAI",
        "importOf": "DsAX04GAEAA",
        "lastUpdated": 0,
        "lastUpdatedBy": null,
        "name": "Service hosts saturation",
        "options": {
          "colorBy": "Scale",
          "colorRange": null,
          "colorScale": null,
          "colorScale2": [
            {
              "gt": 90,
              "gte": null,
              "lt": null,
              "lte": null,
              "paletteIndex": 16
            },
            {
              "gt": 75,
              "gte": null,
              "lt": null,
              "lte": 90,
              "paletteIndex": 17
            },
            {
              "gt": 50,
              "gte": null,
              "lt": null,
              "lte": 75,
              "paletteIndex": 18
            },
            {
              "gt": null,
              "gte": null,
              "lt": null,
              "lte": 50,
              "paletteIndex": 20
            }
          ],
          "groupBy": [],
          "programOptions": {
            "disableSampling": false,
            "maxDelay": 0,
            "minimumResolution": 0
          },
          "publishLabelOptions": [
            {
              "displayName": "cpu.utilization",
              "label": "A",
              "valuePrefix": "",
              "valueSuffix": "",
              "valueUnit": null
            },
            {
              "displayName": "memory.utilization",
              "label": "B",
              "valuePrefix": "",
              "valueSuffix": "",
              "valueUnit": null
            },
            {
              "displayName": "disk.summary_utilization",
              "label": "C",
              "valuePrefix": "",
              "valueSuffix": "",
              "valueUnit": null
            },
            {
              "displayName": "Saturation",
              "label": "D",
              "valuePrefix": "",
              "valueSuffix": "%",
              "valueUnit": null
            }
          ],
          "refreshInterval": null,
          "sortDirection": "Ascending",
          "sortProperty": null,
          "time": {
            "range": 900000,
            "type": "relative"
          },
          "timestampHidden": false,
          "timezone": null,
          "type": "Heatmap",
          "unitPrefix": "Metric"
        },
        "packageSpecifications": "",
        "programText": "A = data('cpu.utilization', filter=filter('sf_hasService', '*')).publish(label='A', enable=False)\nB = data('memory.utilization', filter=filter('sf_hasService', '*')).publish(label='B', enable=False)\nC = data('disk.summary_utilization', filter=filter('sf_hasService', '*')).publish(label='C', enable=False)\nD = max(A,B,C).sum(by='host').publish(label='D')",
        "relatedDetectorIds": [],
        "tags": null
      }
    },
    {
      "chart": {
        "created": 0,
        "creator": null,
        "customProperties": {},
        "description": "Requests/sec processed by the endpoint",
        "id": "DsK5qw1AcAA",
        "importOf": "Dqlm3FxAAAA",
        "lastUpdated": 0,
        "lastUpdatedBy": null,
        "name": "Request rate",
        "options": {
          "areaChartOptions": {
            "showDataMarkers": false
          },
          "axes": [
            {
              "highWatermark": null,
              "highWatermarkLabel": null,
              "label": "",
              "lowWatermark": null,
              "lowWatermarkLabel": null,
              "max": null,
              "min": null
            },
            {
              "highWatermark": null,
              "highWatermarkLabel": null,
              "label": "",
              "lowWatermark": null,
              "lowWatermarkLabel": null,
              "max": null,
              "min": null
            }
          ],
          "axisPrecision": null,
          "colorBy": "Dimension",
          "defaultPlotType": "LineChart",
          "eventPublishLabelOptions": [],
          "histogramChartOptions": {
            "colorThemeIndex": 16
          },
          "includeZero": false,
          "legendOptions": {
            "fields": null
          },
          "lineChartOptions": {
            "showDataMarkers": false
          },
          "onChartLegendOptions": {
            "dimensionInLegend": null,
            "showLegend": false
          },
          "programOptions": {
            "disableSampling": false,
            "maxDelay": null,
            "minimumResolution": 0
          },
          "publishLabelOptions": [
            {
              "displayName": "Requests/sec",
              "label": "A",
              "paletteIndex": null,
              "plotType": null,
              "valuePrefix": null,
              "valueSuffix": "requests/sec",
              "valueUnit": null,
              "yAxis": 0
            }
          ],
          "showEventLines": false,
          "stacked": false,
          "time": {
            "range": 900000,
            "type": "relative"
          },
          "timezone": null,
          "type": "TimeSeriesChart",
          "unitPrefix": "Metric"
        },
        "packageSpecifications": "",
        "programText": "A = data('spans.count', filter=filter('kind', 'SERVER', 'CONSUMER') and filter('service', '*') and filter('operation', '*')).sum(by=['service', 'operation']).publish(label='A')",
        "relatedDetectorIds": [],
        "tags": null
      }
    },
    {
      "chart": {
        "created": 0,
        "creator": null,
        "customProperties": {},
        "description": "Error rate on requests made to the endpoint",
        "id": "DupO7rsAYAA",
        "lastUpdated": 0,
        "lastUpdatedBy": null,
        "name": "Error rate",
        "options": {
          "areaChartOptions": {
            "showDataMarkers": false
          },
          "axes": [
            {
              "highWatermark": null,
              "highWatermarkLabel": null,
              "label": "",
              "lowWatermark": null,
              "lowWatermarkLabel": null,
              "max": null,
              "min": null
            },
            {
              "highWatermark": null,
              "highWatermarkLabel": null,
              "label": "",
              "lowWatermark": null,
              "lowWatermarkLabel": null,
              "max": null,
              "min": null
            }
          ],
          "axisPrecision": null,
          "colorBy": "Dimension",
          "defaultPlotType": "LineChart",
          "eventPublishLabelOptions": [],
          "histogramChartOptions": {
            "colorThemeIndex": 16
          },
          "includeZero": false,
          "legendOptions": {
            "fields": null
          },
          "lineChartOptions": {
            "showDataMarkers": false
          },
          "onChartLegendOptions": {
            "dimensionInLegend": null,
            "showLegend": false
          },
          "programOptions": {
            "disableSampling": false,
            "maxDelay": null,
            "minimumResolution": 0
          },
          "publishLabelOptions": [
            {
              "displayName": "Requests",
              "label": "A",
              "paletteIndex": null,
              "plotType": null,
              "valuePrefix": null,
              "valueSuffix": null,
              "valueUnit": null,
              "yAxis": 0
            },
            {
              "displayName": "Errors",
              "label": "B",
              "paletteIndex": null,
              "plotType": null,
              "valuePrefix": null,
              "valueSuffix": null,
              "valueUnit": null,
              "yAxis": 0
            },
            {
              "displayName": "Error rate",
              "label": "C",
              "paletteIndex": null,
              "plotType": null,
              "valuePrefix": null,
              "valueSuffix": "%",
              "valueUnit": null,
              "yAxis": 0
            }
          ],
          "showEventLines": false,
          "stacked": false,
          "time": {
            "range": 900000,
            "type": "relative"
          },
          "timezone": null,
          "type": "TimeSeriesChart",
          "unitPrefix": "Metric"
        },
        "packageSpecifications": "",
        "programText": "A = data('spans.count', filter=filter('kind', 'SERVER', 'CONSUMER') and filter('error', 'false') and filter('service', '*') and filter('operation', '*')).sum(by=['service', 'operation']).publish(label='A', enable=False)\nB = data('spans.count', filter=filter('kind', 'SERVER', 'CONSUMER') and filter('error', 'true') and filter('service', '*') and filter('operation', '*')).sum(by=['service', 'operation']).publish(label='B', enable=False)\nC = (100*B/A).publish(label='C')",
        "relatedDetectorIds": [],
        "tags": null
      }
    },
    {
      "chart": {
        "created": 0,
        "creator": null,
        "customProperties": {},
        "description": "",
        "id": "DsLqs1OAcAA",
        "lastUpdated": 0,
        "lastUpdatedBy": null,
        "name": "Service map",
        "options": {
          "colorBy": "Range",
          "colorRange": {
            "color": null,
            "max": null,
            "min": null
          },
          "colorScale2": null,
          "defaultColorBy": null,
          "defaultSizeBy": null,
          "mapRange": null,
          "operationFilter": null,
          "programOptions": {
            "disableSampling": false,
            "maxDelay": 0,
            "minimumResolution": 0
          },
          "serviceFilter": [],
          "systemMapLabelOptions": [
            {
              "displayName": "Requests/sec",
              "label": "B",
              "valuePrefix": null,
              "valueSuffix": null,
              "valueUnit": null,
              "viewMenu": "SizeBy"
            }
          ],
          "tagFilters": null,
          "timezone": null,
          "type": "SystemMap"
        },
        "packageSpecifications": "",
        "programText": "B = data('spans.count', filter=filter('kind', 'CONSUMER', 'SERVER')).sum(by=['service']).publish(label='B')",
        "relatedDetectorIds": [],
        "tags": null
      }
    },
    {
      "chart": {
        "created": 0,
        "creator": null,
        "customProperties": {},
        "description": "99th percentile request latency by endpoint",
        "id": "DupMwbOAYAU",
        "lastUpdated": 0,
        "lastUpdatedBy": null,
        "name": "Request latency (p99) by endpoint",
        "options": {
          "areaChartOptions": {
            "showDataMarkers": false
          },
          "axes": [
            {
              "highWatermark": null,
              "highWatermarkLabel": null,
              "label": "",
              "lowWatermark": null,
              "lowWatermarkLabel": null,
              "max": null,
              "min": null
            },
            {
              "highWatermark": null,
              "highWatermarkLabel": null,
              "label": "",
              "lowWatermark": null,
              "lowWatermarkLabel": null,
              "max": null,
              "min": null
            }
          ],
          "axisPrecision": null,
          "colorBy": "Dimension",
          "defaultPlotType": "AreaChart",
          "eventPublishLabelOptions": [],
          "histogramChartOptions": {
            "colorThemeIndex": 16
          },
          "includeZero": false,
          "legendOptions": {
            "fields": null
          },
          "lineChartOptions": {
            "showDataMarkers": false
          },
          "onChartLegendOptions": {
            "dimensionInLegend": null,
            "showLegend": false
          },
          "programOptions": {
            "disableSampling": false,
            "maxDelay": null,
            "minimumResolution": 0
          },
          "publishLabelOptions": [
            {
              "displayName": "Request latency (p99)",
              "label": "A",
              "paletteIndex": null,
              "plotType": null,
              "valuePrefix": null,
              "valueSuffix": null,
              "valueUnit": "Nanosecond",
              "yAxis": 0
            }
          ],
          "showEventLines": false,
          "stacked": true,
          "time": {
            "range": 900000,
            "type": "relative"
          },
          "timezone": null,
          "type": "TimeSeriesChart",
          "unitPrefix": "Metric"
        },
        "packageSpecifications": "",
        "programText": "A = data('spans.duration.ns.p99', filter=filter('kind', 'SERVER', 'CONSUMER') and filter('service', '*')).max(by=['operation', 'service']).publish(label='A')",
        "relatedDetectorIds": [],
        "tags": null
      }
    },
    {
      "chart": {
        "created": 0,
        "creator": null,
        "customProperties": {},
        "description": "99th percentile response time",
        "id": "DsK5n_yAcAE",
        "importOf": "DqlWiSsAEAA",
        "lastUpdated": 0,
        "lastUpdatedBy": null,
        "name": "Request latency (p99)",
        "options": {
          "colorBy": "Metric",
          "colorScale": null,
          "colorScale2": null,
          "maximumPrecision": 6,
          "programOptions": {
            "disableSampling": false,
            "maxDelay": null,
            "minimumResolution": 0
          },
          "publishLabelOptions": [
            {
              "displayName": "p99 latency",
              "label": "A",
              "paletteIndex": null,
              "plotType": null,
              "valuePrefix": null,
              "valueSuffix": null,
              "valueUnit": "Nanosecond",
              "yAxis": 0
            }
          ],
          "refreshInterval": null,
          "secondaryVisualization": "Sparkline",
          "showSparkLine": false,
          "time": {
            "range": 900000,
            "type": "relative"
          },
          "timestampHidden": false,
          "timezone": null,
          "type": "SingleValue",
          "unitPrefix": "Metric"
        },
        "packageSpecifications": "",
        "programText": "A = data('spans.duration.ns.p99', filter=filter('kind', 'CONSUMER', 'SERVER') and filter('service', '*')).mean(by=['service']).publish(label='A')",
        "relatedDetectorIds": [],
        "tags": null
      }
    },
    {
      "chart": {
        "created": 0,
        "creator": null,
        "customProperties": {},
        "description": "Cumulative network utilization of the service hosts",
        "id": "DsK5rM1AcC0",
        "importOf": "DsAXzLYAEAA",
        "lastUpdated": 0,
        "lastUpdatedBy": null,
        "name": "Host network utilization",
        "options": {
          "areaChartOptions": {
            "showDataMarkers": false
          },
          "axes": [
            {
              "highWatermark": null,
              "highWatermarkLabel": null,
              "label": "",
              "lowWatermark": null,
              "lowWatermarkLabel": null,
              "max": null,
              "min": 0
            },
            {
              "highWatermark": null,
              "highWatermarkLabel": null,
              "label": "",
              "lowWatermark": null,
              "lowWatermarkLabel": null,
              "max": null,
              "min": null
            }
          ],
          "axisPrecision": null,
          "colorBy": "Dimension",
          "defaultPlotType": "LineChart",
          "eventPublishLabelOptions": [],
          "histogramChartOptions": {
            "colorThemeIndex": 16
          },
          "includeZero": false,
          "legendOptions": {
            "fields": null
          },
          "lineChartOptions": {
            "showDataMarkers": false
          },
          "onChartLegendOptions": {
            "dimensionInLegend": null,
            "showLegend": false
          },
          "programOptions": {
            "disableSampling": false,
            "maxDelay": 0,
            "minimumResolution": 0
          },
          "publishLabelOptions": [
            {
              "displayName": "Network utilization",
              "label": "A",
              "paletteIndex": null,
              "plotType": null,
              "valuePrefix": null,
              "valueSuffix": null,
              "valueUnit": "Byte",
              "yAxis": 0
            }
          ],
          "showEventLines": false,
          "stacked": false,
          "time": {
            "range": 900000,
            "type": "relative"
          },
          "timezone": null,
          "type": "TimeSeriesChart",
          "unitPrefix": "Metric"
        },
        "packageSpecifications": "",
        "programText": "A = data('network.total', filter=filter('sf_hasService', '*')).publish(label='A')",
        "relatedDetectorIds": [],
        "tags": null
      }
    },
    {
      "chart": {
        "created": 0,
        "creator": null,
        "customProperties": {},
        "description": "Disk utilization of the service hosts",
        "id": "DsK5p-LAcAk",
        "importOf": "Dr_82RWAEAA",
        "lastUpdated": 0,
        "lastUpdatedBy": null,
        "name": "Host disk usage",
        "options": {
          "areaChartOptions": {
            "showDataMarkers": false
          },
          "axes": [
            {
              "highWatermark": null,
              "highWatermarkLabel": null,
              "label": "%",
              "lowWatermark": null,
              "lowWatermarkLabel": null,
              "max": 100,
              "min": 0
            },
            {
              "highWatermark": null,
              "highWatermarkLabel": null,
              "label": "",
              "lowWatermark": null,
              "lowWatermarkLabel": null,
              "max": null,
              "min": null
            }
          ],
          "axisPrecision": null,
          "colorBy": "Dimension",
          "defaultPlotType": "LineChart",
          "eventPublishLabelOptions": [],
          "histogramChartOptions": {
            "colorThemeIndex": 16
          },
          "includeZero": false,
          "legendOptions": {
            "fields": null
          },
          "lineChartOptions": {
            "showDataMarkers": false
          },
          "onChartLegendOptions": {
            "dimensionInLegend": null,
            "showLegend": false
          },
          "programOptions": {
            "disableSampling": false,
            "maxDelay": 0,
            "minimumResolution": 0
          },
          "publishLabelOptions": [
            {
              "displayName": "disk.summary_utilization",
              "label": "A",
              "paletteIndex": null,
              "plotType": null,
              "valuePrefix": "",
              "valueSuffix": "",
              "valueUnit": null,
              "yAxis": 0
            }
          ],
          "showEventLines": false,
          "stacked": false,
          "time": {
            "range": 900000,
            "type": "relative"
          },
          "timezone": null,
          "type": "TimeSeriesChart",
          "unitPrefix": "Metric"
        },
        "packageSpecifications": "",
        "programText": "A = data('disk.summary_utilization', filter=filter('sf_hasService', '*')).publish(label='A')",
        "relatedDetectorIds": [],
        "tags": null
      }
    },
    {
      "chart": {
        "created": 0,
        "creator": null,
        "customProperties": {},
        "description": "CPU Utilization of the service hosts",
        "id": "DsK5pAvAcEA",
        "importOf": "DrmkvA5AIAA",
        "lastUpdated": 0,
        "lastUpdatedBy": null,
        "name": "Host CPU",
        "options": {
          "areaChartOptions": {
            "showDataMarkers": false
          },
          "axes": [
            {
              "highWatermark": null,
              "highWatermarkLabel": null,
              "label": "%",
              "lowWatermark": null,
              "lowWatermarkLabel": null,
              "max": 100,
              "min": 0
            },
            {
              "highWatermark": null,
              "highWatermarkLabel": null,
              "label": "",
              "lowWatermark": null,
              "lowWatermarkLabel": null,
              "max": null,
              "min": null
            }
          ],
          "axisPrecision": null,
          "colorBy": "Dimension",
          "defaultPlotType": "LineChart",
          "eventPublishLabelOptions": [],
          "histogramChartOptions": {
            "colorThemeIndex": 16
          },
          "includeZero": false,
          "legendOptions": {
            "fields": null
          },
          "lineChartOptions": {
            "showDataMarkers": false
          },
          "onChartLegendOptions": {
            "dimensionInLegend": null,
            "showLegend": false
          },
          "programOptions": {
            "disableSampling": false,
            "maxDelay": 0,
            "minimumResolution": 0
          },
          "publishLabelOptions": [
            {
              "displayName": "cpu.utilization",
              "label": "A",
              "paletteIndex": null,
              "plotType": null,
              "valuePrefix": "",
              "valueSuffix": "",
              "valueUnit": null,
              "yAxis": 0
            }
          ],
          "showEventLines": false,
          "stacked": false,
          "time": {
            "range": 900000,
            "type": "relative"
          },
          "timezone": null,
          "type": "TimeSeriesChart",
          "unitPrefix": "Metric"
        },
        "packageSpecifications": "",
        "programText": "A = data('cpu.utilization', filter=filter('sf_hasService', '*')).publish(label='A')",
        "relatedDetectorIds": [],
        "tags": null
      }
    },
    {
      "chart": {
        "created": 0,
        "creator": null,
        "customProperties": {},
        "description": "Requests/sec processed by the endpoint",
        "id": "DsK5oKLAcAA",
        "importOf": "DqlkkagAEAA",
        "lastUpdated": 0,
        "lastUpdatedBy": null,
        "name": "Request rate",
        "options": {
          "colorBy": "Dimension",
          "colorScale": null,
          "colorScale2": null,
          "maximumPrecision": 4,
          "programOptions": {
            "disableSampling": false,
            "maxDelay": null,
            "minimumResolution": 0
          },
          "publishLabelOptions": [
            {
              "displayName": "Requests/sec",
              "label": "A",
              "paletteIndex": null,
              "plotType": null,
              "valuePrefix": null,
              "valueSuffix": "requests/sec",
              "valueUnit": null,
              "yAxis": 0
            }
          ],
          "refreshInterval": null,
          "secondaryVisualization": "None",
          "showSparkLine": false,
          "time": {
            "range": 900000,
            "type": "relative"
          },
          "timestampHidden": false,
          "timezone": null,
          "type": "SingleValue",
          "unitPrefix": "Metric"
        },
        "packageSpecifications": "",
        "programText": "A = data('spans.count', filter=filter('kind', 'SERVER', 'CONSUMER') and filter('service', '*') and filter('operation', '*')).sum(by=['service', 'operation']).publish(label='A')",
        "relatedDetectorIds": [],
        "tags": null
      }
    },
    {
      "chart": {
        "created": 0,
        "creator": null,
        "customProperties": {},
        "description": "Error rate on requests made to the service",
        "id": "DupMeGOAcAA",
        "lastUpdated": 0,
        "lastUpdatedBy": null,
        "name": "Error rate",
        "options": {
          "areaChartOptions": {
            "showDataMarkers": false
          },
          "axes": [
            {
              "highWatermark": null,
              "highWatermarkLabel": null,
              "label": "",
              "lowWatermark": null,
              "lowWatermarkLabel": null,
              "max": null,
              "min": null
            },
            {
              "highWatermark": null,
              "highWatermarkLabel": null,
              "label": "",
              "lowWatermark": null,
              "lowWatermarkLabel": null,
              "max": null,
              "min": null
            }
          ],
          "axisPrecision": null,
          "colorBy": "Dimension",
          "defaultPlotType": "LineChart",
          "eventPublishLabelOptions": [],
          "histogramChartOptions": {
            "colorThemeIndex": 16
          },
          "includeZero": false,
          "legendOptions": {
            "fields": null
          },
          "lineChartOptions": {
            "showDataMarkers": false
          },
          "onChartLegendOptions": {
            "dimensionInLegend": null,
            "showLegend": false
          },
          "programOptions": {
            "disableSampling": false,
            "maxDelay": null,
            "minimumResolution": 0
          },
          "publishLabelOptions": [
            {
              "displayName": "Requests",
              "label": "A",
              "paletteIndex": null,
              "plotType": null,
              "valuePrefix": null,
              "valueSuffix": null,
              "valueUnit": null,
              "yAxis": 0
            },
            {
              "displayName": "Errors",
              "label": "B",
              "paletteIndex": null,
              "plotType": null,
              "valuePrefix": null,
              "valueSuffix": null,
              "valueUnit": null,
              "yAxis": 0
            },
            {
              "displayName": "Error rate",
              "label": "C",
              "paletteIndex": null,
              "plotType": null,
              "valuePrefix": null,
              "valueSuffix": "%",
              "valueUnit": null,
              "yAxis": 0
            }
          ],
          "showEventLines": false,
          "stacked": false,
          "time": {
            "range": 900000,
            "type": "relative"
          },
          "timezone": null,
          "type": "TimeSeriesChart",
          "unitPrefix": "Metric"
        },
        "packageSpecifications": "",
        "programText": "A = data('spans.count', filter=filter('kind', 'SERVER', 'CONSUMER') and filter('error', 'false') and filter('service', '*')).sum(by=['service']).publish(label='A', enable=False)\nB = data('spans.count', filter=filter('kind', 'SERVER', 'CONSUMER') and filter('error', 'true') and filter('service', '*')).sum(by=['service']).publish(label='B', enable=False)\nC = (100*B/A).publish(label='C')",
        "relatedDetectorIds": [],
        "tags": null
      }
    },
    {
      "chart": {
        "created": 0,
        "creator": null,
        "customProperties": {},
        "description": "Requests/sec by service endpoint",
        "id": "DsK5o_5AcBM",
        "importOf": "DqlZIz5AEAA",
        "lastUpdated": 0,
        "lastUpdatedBy": null,
        "name": "Request rate by endpoint",
        "options": {
          "areaChartOptions": {
            "showDataMarkers": false
          },
          "axes": [
            {
              "highWatermark": null,
              "highWatermarkLabel": null,
              "label": "",
              "lowWatermark": null,
              "lowWatermarkLabel": null,
              "max": null,
              "min": null
            },
            {
              "highWatermark": null,
              "highWatermarkLabel": null,
              "label": "",
              "lowWatermark": null,
              "lowWatermarkLabel": null,
              "max": null,
              "min": null
            }
          ],
          "axisPrecision": null,
          "colorBy": "Dimension",
          "defaultPlotType": "AreaChart",
          "eventPublishLabelOptions": [],
          "histogramChartOptions": {
            "colorThemeIndex": 16
          },
          "includeZero": false,
          "legendOptions": {
            "fields": null
          },
          "lineChartOptions": {
            "showDataMarkers": false
          },
          "onChartLegendOptions": {
            "dimensionInLegend": null,
            "showLegend": false
          },
          "programOptions": {
            "disableSampling": false,
            "maxDelay": null,
            "minimumResolution": 0
          },
          "publishLabelOptions": [
            {
              "displayName": "Requests/sec",
              "label": "A",
              "paletteIndex": null,
              "plotType": null,
              "valuePrefix": null,
              "valueSuffix": "requests/sec",
              "valueUnit": null,
              "yAxis": 0
            }
          ],
          "showEventLines": false,
          "stacked": true,
          "time": {
            "range": 900000,
            "type": "relative"
          },
          "timezone": null,
          "type": "TimeSeriesChart",
          "unitPrefix": "Metric"
        },
        "packageSpecifications": "",
        "programText": "A = data('spans.count', filter=filter('kind', 'SERVER', 'CONSUMER') and filter('service', '*')).sum(by=['operation', 'service']).publish(label='A')",
        "relatedDetectorIds": [],
        "tags": null
      }
    },
    {
      "chart": {
        "created": 0,
        "creator": null,
        "customProperties": {},
        "description": "Distribution of request latency with median (50th), 90th and 99th percentiles",
        "id": "DsK5qW7AcAA",
        "importOf": "DqlPwQoAIAA",
        "lastUpdated": 0,
        "lastUpdatedBy": null,
        "name": "Request latency distribution",
        "options": {
          "areaChartOptions": {
            "showDataMarkers": false
          },
          "axes": [
            {
              "highWatermark": null,
              "highWatermarkLabel": null,
              "label": "",
              "lowWatermark": null,
              "lowWatermarkLabel": null,
              "max": null,
              "min": null
            },
            {
              "highWatermark": null,
              "highWatermarkLabel": null,
              "label": "",
              "lowWatermark": null,
              "lowWatermarkLabel": null,
              "max": null,
              "min": null
            }
          ],
          "axisPrecision": null,
          "colorBy": "Metric",
          "defaultPlotType": "AreaChart",
          "eventPublishLabelOptions": [],
          "histogramChartOptions": {
            "colorThemeIndex": 16
          },
          "includeZero": false,
          "legendOptions": {
            "fields": null
          },
          "lineChartOptions": {
            "showDataMarkers": false
          },
          "onChartLegendOptions": {
            "dimensionInLegend": null,
            "showLegend": false
          },
          "programOptions": {
            "disableSampling": false,
            "maxDelay": null,
            "minimumResolution": 0
          },
          "publishLabelOptions": [
            {
              "displayName": "p50 latency",
              "label": "A",
              "paletteIndex": null,
              "plotType": null,
              "valuePrefix": null,
              "valueSuffix": null,
              "valueUnit": "Nanosecond",
              "yAxis": 0
            },
            {
              "displayName": "p90 latency",
              "label": "B",
              "paletteIndex": null,
              "plotType": null,
              "valuePrefix": null,
              "valueSuffix": null,
              "valueUnit": "Nanosecond",
              "yAxis": 0
            },
            {
              "displayName": "p99 latency",
              "label": "C",
              "paletteIndex": null,
              "plotType": null,
              "valuePrefix": null,
              "valueSuffix": null,
              "valueUnit": "Nanosecond",
              "yAxis": 0
            }
          ],
          "showEventLines": false,
          "stacked": false,
          "time": {
            "range": 900000,
            "type": "relative"
          },
          "timezone": null,
          "type": "TimeSeriesChart",
          "unitPrefix": "Metric"
        },
        "packageSpecifications": "",
        "programText": "A = data('spans.duration.ns.median', filter=filter('kind', 'CONSUMER', 'SERVER') and filter('service', '*')).mean(by=['service']).publish(label='A')\nB = data('spans.duration.ns.p90', filter=filter('kind', 'CONSUMER', 'SERVER') and filter('service', '*')).mean(by=['service']).publish(label='B')\nC = data('spans.duration.ns.p99', filter=filter('kind', 'CONSUMER', 'SERVER') and filter('service', '*')).mean(by=['service']).publish(label='C')",
        "relatedDetectorIds": [],
        "tags": null
      }
    },
    {
      "chart": {
        "created": 0,
        "creator": null,
        "customProperties": {},
        "description": "",
        "id": "DsK5op5AcAk",
        "importOf": "DqlWiS_AIAA",
        "lastUpdated": 0,
        "lastUpdatedBy": null,
        "name": "Service map",
        "options": {
          "colorBy": "Range",
          "colorRange": {
            "color": null,
            "max": null,
            "min": null
          },
          "colorScale2": null,
          "defaultColorBy": null,
          "defaultSizeBy": null,
          "mapRange": null,
          "operationFilter": null,
          "programOptions": {
            "disableSampling": false,
            "maxDelay": 0,
            "minimumResolution": 0
          },
          "serviceFilter": [],
          "systemMapLabelOptions": [
            {
              "displayName": "Requests/sec",
              "label": "B",
              "valuePrefix": null,
              "valueSuffix": null,
              "valueUnit": null,
              "viewMenu": "SizeBy"
            }
          ],
          "tagFilters": null,
          "timezone": null,
          "type": "SystemMap"
        },
        "packageSpecifications": "",
        "programText": "B = data('spans.count', filter=filter('kind', 'CONSUMER', 'SERVER')).sum(by=['service']).publish(label='B')",
        "relatedDetectorIds": [],
        "tags": null
      }
    },
    {
      "chart": {
        "created": 0,
        "creator": null,
        "customProperties": {},
        "description": "Requests/sec processed by the service",
        "id": "DsK5pwsAcBc",
        "importOf": "DqlPwYiAAAA",
        "lastUpdated": 0,
        "lastUpdatedBy": null,
        "name": "Request rate",
        "options": {
          "colorBy": "Dimension",
          "colorScale": null,
          "colorScale2": null,
          "maximumPrecision": 4,
          "programOptions": {
            "disableSampling": false,
            "maxDelay": null,
            "minimumResolution": 0
          },
          "publishLabelOptions": [
            {
              "displayName": "Requests/sec",
              "label": "A",
              "paletteIndex": null,
              "plotType": null,
              "valuePrefix": null,
              "valueSuffix": "requests/sec",
              "valueUnit": null,
              "yAxis": 0
            }
          ],
          "refreshInterval": null,
          "secondaryVisualization": "None",
          "showSparkLine": false,
          "time": {
            "range": 900000,
            "type": "relative"
          },
          "timestampHidden": false,
          "timezone": null,
          "type": "SingleValue",
          "unitPrefix": "Metric"
        },
        "packageSpecifications": "",
        "programText": "A = data('spans.count', filter=filter('kind', 'SERVER', 'CONSUMER') and filter('service', '*')).sum(by=['service']).publish(label='A')",
        "relatedDetectorIds": [],
        "tags": null
      }
    },
    {
      "chart": {
        "created": 0,
        "creator": null,
        "customProperties": {},
        "description": "Error rate on requests made to the endpoint",
        "id": "DsK5pEEAcAw",
        "importOf": "DqlkkibAIAA",
        "lastUpdated": 0,
        "lastUpdatedBy": null,
        "name": "Error rate",
        "options": {
          "colorBy": "Dimension",
          "colorScale": null,
          "colorScale2": null,
          "maximumPrecision": null,
          "programOptions": {
            "disableSampling": false,
            "maxDelay": null,
            "minimumResolution": 0
          },
          "publishLabelOptions": [
            {
              "displayName": "Requests",
              "label": "A",
              "paletteIndex": null,
              "plotType": null,
              "valuePrefix": null,
              "valueSuffix": null,
              "valueUnit": null,
              "yAxis": 0
            },
            {
              "displayName": "Errors",
              "label": "B",
              "paletteIndex": null,
              "plotType": null,
              "valuePrefix": null,
              "valueSuffix": null,
              "valueUnit": null,
              "yAxis": 0
            },
            {
              "displayName": "Error rate",
              "label": "C",
              "paletteIndex": null,
              "plotType": null,
              "valuePrefix": null,
              "valueSuffix": "%",
              "valueUnit": null,
              "yAxis": 0
            }
          ],
          "refreshInterval": null,
          "secondaryVisualization": "None",
          "showSparkLine": false,
          "time": {
            "range": 900000,
            "type": "relative"
          },
          "timestampHidden": false,
          "timezone": null,
          "type": "SingleValue",
          "unitPrefix": "Metric"
        },
        "packageSpecifications": "",
        "programText": "A = data('spans.count', filter=filter('kind', 'SERVER', 'CONSUMER') and filter('error', 'false') and filter('service', '*') and filter('operation', '*')).sum(by=['service', 'operation']).publish(label='A', enable=False)\nB = data('spans.count', filter=filter('kind', 'SERVER', 'CONSUMER') and filter('error', 'true') and filter('service', '*') and filter('operation', '*')).sum(by=['service', 'operation']).publish(label='B', enable=False)\nC = (100*B/A).publish(label='C')",
        "relatedDetectorIds": [],
        "tags": null
      }
    },
    {
      "chart": {
        "created": 0,
        "creator": null,
        "customProperties": {},
        "description": "Saturation of the service hosts (max of CPU, memory and disk utilization)",
        "id": "DupMwDxAcAA",
        "lastUpdated": 0,
        "lastUpdatedBy": null,
        "name": "Service hosts saturation",
        "options": {
          "colorBy": "Scale",
          "colorRange": null,
          "colorScale": null,
          "colorScale2": [
            {
              "gt": 90,
              "gte": null,
              "lt": null,
              "lte": null,
              "paletteIndex": 16
            },
            {
              "gt": 75,
              "gte": null,
              "lt": null,
              "lte": 90,
              "paletteIndex": 17
            },
            {
              "gt": 50,
              "gte": null,
              "lt": null,
              "lte": 75,
              "paletteIndex": 18
            },
            {
              "gt": null,
              "gte": null,
              "lt": null,
              "lte": 50,
              "paletteIndex": 20
            }
          ],
          "groupBy": [],
          "programOptions": {
            "disableSampling": false,
            "maxDelay": 0,
            "minimumResolution": 0
          },
          "publishLabelOptions": [
            {
              "displayName": "cpu.utilization",
              "label": "A",
              "valuePrefix": "",
              "valueSuffix": "",
              "valueUnit": null
            },
            {
              "displayName": "memory.utilization",
              "label": "B",
              "valuePrefix": "",
              "valueSuffix": "",
              "valueUnit": null
            },
            {
              "displayName": "disk.summary_utilization",
              "label": "C",
              "valuePrefix": "",
              "valueSuffix": "",
              "valueUnit": null
            },
            {
              "displayName": "Saturation",
              "label": "D",
              "valuePrefix": "",
              "valueSuffix": "%",
              "valueUnit": null
            }
          ],
          "refreshInterval": null,
          "sortDirection": "Ascending",
          "sortProperty": null,
          "time": {
            "range": 900000,
            "type": "relative"
          },
          "timestampHidden": false,
          "timezone": null,
          "type": "Heatmap",
          "unitPrefix": "Metric"
        },
        "packageSpecifications": "",
        "programText": "A = data('cpu.utilization', filter=filter('sf_hasService', '*')).publish(label='A', enable=False)\nB = data('memory.utilization', filter=filter('sf_hasService', '*')).publish(label='B', enable=False)\nC = data('disk.summary_utilization', filter=filter('sf_hasService', '*')).publish(label='C',enable=False)\nD = max(A,B,C).sum(by='host').publish(label='D')",
        "relatedDetectorIds": [],
        "tags": null
      }
    },
    {
      "chart": {
        "created": 0,
        "creator": null,
        "customProperties": {},
        "description": "Error rate on requests made to the service, by endpoint",
        "id": "DupNKpxAYAA",
        "lastUpdated": 0,
        "lastUpdatedBy": null,
        "name": "Error rate by endpoint",
        "options": {
          "areaChartOptions": {
            "showDataMarkers": false
          },
          "axes": [
            {
              "highWatermark": null,
              "highWatermarkLabel": null,
              "label": "",
              "lowWatermark": null,
              "lowWatermarkLabel": null,
              "max": null,
              "min": null
            },
            {
              "highWatermark": null,
              "highWatermarkLabel": null,
              "label": "",
              "lowWatermark": null,
              "lowWatermarkLabel": null,
              "max": null,
              "min": null
            }
          ],
          "axisPrecision": null,
          "colorBy": "Dimension",
          "defaultPlotType": "LineChart",
          "eventPublishLabelOptions": [],
          "histogramChartOptions": {
            "colorThemeIndex": 16
          },
          "includeZero": false,
          "legendOptions": {
            "fields": null
          },
          "lineChartOptions": {
            "showDataMarkers": false
          },
          "onChartLegendOptions": {
            "dimensionInLegend": null,
            "showLegend": false
          },
          "programOptions": {
            "disableSampling": false,
            "maxDelay": null,
            "minimumResolution": 0
          },
          "publishLabelOptions": [
            {
              "displayName": "Requests",
              "label": "A",
              "paletteIndex": null,
              "plotType": null,
              "valuePrefix": null,
              "valueSuffix": null,
              "valueUnit": null,
              "yAxis": 0
            },
            {
              "displayName": "Errors",
              "label": "B",
              "paletteIndex": null,
              "plotType": null,
              "valuePrefix": null,
              "valueSuffix": null,
              "valueUnit": null,
              "yAxis": 0
            },
            {
              "displayName": "Error rate",
              "label": "C",
              "paletteIndex": null,
              "plotType": null,
              "valuePrefix": null,
              "valueSuffix": "%",
              "valueUnit": null,
              "yAxis": 0
            }
          ],
          "showEventLines": false,
          "stacked": false,
          "time": {
            "range": 900000,
            "type": "relative"
          },
          "timezone": null,
          "type": "TimeSeriesChart",
          "unitPrefix": "Metric"
        },
        "packageSpecifications": "",
        "programText": "A = data('spans.count', filter=filter('kind', 'SERVER', 'CONSUMER') and filter('error', 'false') and filter('service', '*')).sum(by=['operation', 'service']).publish(label='A', enable=False)\nB = data('spans.count', filter=filter('kind', 'SERVER', 'CONSUMER') and filter('error', 'true') and filter('service', '*')).sum(by=['operation', 'service']).publish(label='B', enable=False)\nC = (100*B/A).publish(label='C')",
        "relatedDetectorIds": [],
        "tags": null
      }
    },
    {
      "chart": {
        "created": 0,
        "creator": null,
        "customProperties": {},
        "description": "Memory utilization of the service hosts",
        "id": "DsK5rX4AcC4",
        "importOf": "DsAX046AIAA",
        "lastUpdated": 0,
        "lastUpdatedBy": null,
        "name": "Host memory usage",
        "options": {
          "areaChartOptions": {
            "showDataMarkers": false
          },
          "axes": [
            {
              "highWatermark": null,
              "highWatermarkLabel": null,
              "label": "%",
              "lowWatermark": null,
              "lowWatermarkLabel": null,
              "max": 100,
              "min": 0
            },
            {
              "highWatermark": null,
              "highWatermarkLabel": null,
              "label": "",
              "lowWatermark": null,
              "lowWatermarkLabel": null,
              "max": null,
              "min": null
            }
          ],
          "axisPrecision": null,
          "colorBy": "Dimension",
          "defaultPlotType": "LineChart",
          "eventPublishLabelOptions": [],
          "histogramChartOptions": {
            "colorThemeIndex": 16
          },
          "includeZero": false,
          "legendOptions": {
            "fields": null
          },
          "lineChartOptions": {
            "showDataMarkers": false
          },
          "onChartLegendOptions": {
            "dimensionInLegend": null,
            "showLegend": false
          },
          "programOptions": {
            "disableSampling": false,
            "maxDelay": 0,
            "minimumResolution": 0
          },
          "publishLabelOptions": [
            {
              "displayName": "memory.utilization",
              "label": "A",
              "paletteIndex": null,
              "plotType": null,
              "valuePrefix": "",
              "valueSuffix": "",
              "valueUnit": null,
              "yAxis": 0
            }
          ],
          "showEventLines": false,
          "stacked": false,
          "time": {
            "range": 900000,
            "type": "relative"
          },
          "timezone": null,
          "type": "TimeSeriesChart",
          "unitPrefix": "Metric"
        },
        "packageSpecifications": "",
        "programText": "A = data('memory.utilization', filter=filter('sf_hasService', '*')).publish(label='A')",
        "relatedDetectorIds": [],
        "tags": null
      }
    }
  ],
  "crossLinkExports": [
    {
      "crossLink": {
        "created": 0,
        "creator": null,
        "id": "DsK5uFfAcIk",
        "lastUpdated": 0,
        "lastUpdatedBy": null,
        "propertyName": "service",
        "propertyValue": "",
        "targets": [
          {
            "dashboardGroupId": "DsK5nuJAcAA",
            "dashboardId": "DsK5tQFAcEo",
            "isDefault": true,
            "name": "APM Service",
            "type": "INTERNAL_LINK"
          }
        ]
      }
    }
  ],
  "dashboardExports": [
    {
      "dashboard": {
        "chartDensity": "DEFAULT",
        "charts": [
          {
            "chartId": "DsK5op5AcAk",
            "column": 0,
            "height": 3,
            "row": 0,
            "width": 5
          },
          {
            "chartId": "DsK5pwsAcBc",
            "column": 5,
            "height": 1,
            "row": 0,
            "width": 3
          },
          {
            "chartId": "DsK5oLZAcAA",
            "column": 8,
            "height": 1,
            "row": 0,
            "width": 4
          },
          {
            "chartId": "DsK5n_yAcAE",
            "column": 5,
            "height": 1,
            "row": 1,
            "width": 3
          },
          {
            "chartId": "DsK5qW7AcAA",
            "column": 8,
            "height": 1,
            "row": 1,
            "width": 4
          },
          {
            "chartId": "DsK5qJnAcA8",
            "column": 5,
            "height": 1,
            "row": 2,
            "width": 3
          },
          {
            "chartId": "DupMeGOAcAA",
            "column": 8,
            "height": 1,
            "row": 2,
            "width": 4
          },
          {
            "chartId": "DupMwbOAYAU",
            "column": 0,
            "height": 1,
            "row": 3,
            "width": 4
          },
          {
            "chartId": "DsK5o_5AcBM",
            "column": 4,
            "height": 1,
            "row": 3,
            "width": 4
          },
          {
            "chartId": "DupNKpxAYAA",
            "column": 8,
            "height": 1,
            "row": 3,
            "width": 4
          },
          {
            "chartId": "DupNkWLAcAA",
            "column": 0,
            "height": 1,
            "row": 4,
            "width": 6
          },
          {
            "chartId": "DupMwDxAcAA",
            "column": 6,
            "height": 1,
            "row": 4,
            "width": 6
          },
          {
            "chartId": "DsK5pd_AcFg",
            "column": 6,
            "height": 1,
            "row": 5,
            "width": 6
          },
          {
            "chartId": "DsK5pAvAcEA",
            "column": 0,
            "height": 1,
            "row": 5,
            "width": 6
          },
          {
            "chartId": "DsK5rG5AcAE",
            "column": 6,
            "height": 1,
            "row": 6,
            "width": 6
          },
          {
            "chartId": "DsK5p-LAcAk",
            "column": 0,
            "height": 1,
            "row": 6,
            "width": 6
          }
        ],
        "created": 0,
        "creator": null,
        "customProperties": null,
        "description": "",
        "discoveryOptions": null,
        "eventOverlays": null,
        "filters": {
          "sources": null,
          "time": null,
          "variables": [
            {
              "alias": "Service",
              "applyIfExists": false,
              "description": "Service name",
              "preferredSuggestions": [],
              "property": "service",
              "replaceOnly": true,
              "required": true,
              "restricted": false,
              "value": "Choose Service"
            }
          ]
        },
        "groupId": "DsK5nuJAcAA",
        "id": "DsK5tQFAcEo",
        "importOf": "DqlPv44AIAA",
        "lastUpdated": 0,
        "lastUpdatedBy": null,
        "locked": false,
        "maxDelayOverride": null,
        "name": "Service",
        "selectedEventOverlays": [],
        "tags": null
      }
    },
    {
      "dashboard": {
        "chartDensity": "HIGH",
        "charts": [
          {
            "chartId": "DsK5oKLAcAA",
            "column": 5,
            "height": 1,
            "row": 0,
            "width": 3
          },
          {
            "chartId": "DsLqs1OAcAA",
            "column": 0,
            "height": 2,
            "row": 0,
            "width": 5
          },
          {
            "chartId": "DsK5qw1AcAA",
            "column": 8,
            "height": 1,
            "row": 0,
            "width": 4
          },
          {
            "chartId": "DsK5of0AcAA",
            "column": 5,
            "height": 1,
            "row": 1,
            "width": 3
          },
          {
            "chartId": "DsK5pkeAcEo",
            "column": 8,
            "height": 1,
            "row": 1,
            "width": 4
          },
          {
            "chartId": "DsK5pEEAcAw",
            "column": 5,
            "height": 1,
            "row": 2,
            "width": 3
          },
          {
            "chartId": "DsK5ou1AcAI",
            "column": 0,
            "height": 1,
            "row": 2,
            "width": 5
          },
          {
            "chartId": "DupO7rsAYAA",
            "column": 8,
            "height": 1,
            "row": 2,
            "width": 4
          },
          {
            "chartId": "DsK5rX4AcC4",
            "column": 6,
            "height": 1,
            "row": 3,
            "width": 6
          },
          {
            "chartId": "DupO1ITAgAA",
            "column": 0,
            "height": 1,
            "row": 3,
            "width": 6
          },
          {
            "chartId": "DsK5owAAcGI",
            "column": 0,
            "height": 1,
            "row": 4,
            "width": 6
          },
          {
            "chartId": "DsK5rM1AcC0",
            "column": 6,
            "height": 1,
            "row": 4,
            "width": 6
          }
        ],
        "created": 0,
        "creator": null,
        "customProperties": null,
        "description": "",
        "discoveryOptions": null,
        "eventOverlays": null,
        "filters": {
          "sources": null,
          "time": null,
          "variables": [
            {
              "alias": "Service",
              "applyIfExists": false,
              "description": "Service name",
              "preferredSuggestions": [],
              "property": "service",
              "replaceOnly": true,
              "required": true,
              "restricted": false,
              "value": "Choose Service"
            },
            {
              "alias": "Endpoint/Operation",
              "applyIfExists": false,
              "description": "Operation or endpoint name",
              "preferredSuggestions": [],
              "property": "operation",
              "replaceOnly": true,
              "required": true,
              "restricted": false,
              "value": "Choose Endpoint"
            }
          ]
        },
        "groupId": "DsK5nuJAcAA",
        "id": "DsK5tKbAcC4",
        "importOf": "DqlkkyTAEAA",
        "lastUpdated": 0,
        "lastUpdatedBy": null,
        "locked": false,
        "maxDelayOverride": null,
        "name": "Service Endpoint",
        "selectedEventOverlays": [],
        "tags": null
      }
    }
  ],
  "groupExport": {
    "group": {
      "created": 0,
      "creator": null,
      "dashboards": [
        "DsK5tKbAcC4",
        "DsK5tQFAcEo"
      ],
      "description": "Microservices APM dashboards",
      "email": null,
      "id": "DsK5nuJAcAA",
      "importDetails": {
        "hashCode": 436523053,
        "importOf": "DqlPvw9AEAA",
        "importTime": 1542421680730
      },
      "importOf": "DqlPvw9AEAA",
      "importQualifiers": [
        {
          "filters": [],
          "metric": "spans.count"
        }
      ],
      "lastUpdated": 0,
      "lastUpdatedBy": null,
      "name": "APM",
      "teams": null
    }
  },
  "hashCode": -1874994333,
  "id": "DsK5nuJAcAA",
  "modelVersion": 1,
  "packageType": "GROUP"
}